pyrum.py
pyrum-0.3.0.dist-info/LICENSE
pyrum-0.3.0.dist-info/METADATA
pyrum-0.3.0.dist-info/WHEEL
pyrum-0.3.0.dist-info/top_level.txt
pyrum-0.3.0.dist-info/RECORD
