Metadata-Version: 2.1
Name: pyrum
Version: 0.3.0
Summary: Python interface for Rumor - Eth2 networking shell
Home-page: https://github.com/protolambda/pyrum
Author: protolambda
Author-email: proto+pip@protolambda.com
License: MIT
Keywords: rumor,networking,libp2peth2
Platform: UNKNOWN
Classifier: Development Status :: 4 - Beta
Classifier: Intended Audience :: Developers
Classifier: License :: OSI Approved :: MIT License
Classifier: Natural Language :: English
Classifier: Programming Language :: Python :: 3
Classifier: Programming Language :: Python :: 3.8
Classifier: Programming Language :: Python :: Implementation :: PyPy
Classifier: Operating System :: OS Independent
Requires-Python: >=3.8, <4
Requires-Dist: trio (==0.13.0)
Requires-Dist: trio-websocket (==0.8.0)
